pyrca/__init__.py
pyrca/test.py
pyrca/analysis/__init__.py
pyrca/analysis/beam_analyses.py
pyrca/analysis/beam_analysis_result.py
pyrca/analysis/stress_distribution.py
pyrca/analysis/beam/__init__.py
pyrca/analysis/beam/beam_analyses.py
pyrca/analysis/beam/beam_analysis_result.py
pyrca/analysis/beam/stress_distribution.py
pyrca/analysis/beam/test/__init__.py
pyrca/analysis/beam/test/test_beam_analysis.py
pyrca/properties/__init__.py
pyrca/properties/beam_section.py
pyrca/properties/node.py
pyrca/properties/section.py
pyrca/properties/steel_compression.py
pyrca/properties/steel_tension.py
pyrca/properties/unit.py
pyrca/properties/beam/__init__.py
pyrca/properties/beam/beam_section.py
pyrca/properties/beam/node.py
pyrca/properties/beam/section.py
pyrca/properties/beam/steel_compression.py
pyrca/properties/beam/steel_tension.py
pyrca/utils/__init__.py
pyrca/utils/beam_constants.py
pyrca/utils/calculators.py
pyrca/utils/constants.py
pyrca/utils/conversion.py
pyrca/utils/test/__init__.py
pyrca/utils/test/test_calculators.py
pyrca/utils/test/test_conversion.py
pyrca-0.2.2.dist-info/LICENSE
pyrca-0.2.2.dist-info/METADATA
pyrca-0.2.2.dist-info/WHEEL
pyrca-0.2.2.dist-info/top_level.txt
pyrca-0.2.2.dist-info/RECORD
