Metadata-Version: 2.1
Name: pyrca
Version: 0.2.2
Summary: Python package for analysis of concrete structures.
Home-page: https://github.com/syncsoft-solutions/pyrca
Author: Alexius Sayco Academia
Author-email: alexius.academia@gmail.com
License: UNKNOWN
Platform: UNKNOWN
Classifier: Programming Language :: Python :: 3
Classifier: License :: OSI Approved :: MIT License
Classifier: Operating System :: OS Independent
Requires-Python: >=3.6
